app.py
cli.py
core.py
global_hotkey_listener.py
filestoai-1.0.0.dist-info/licenses/LICENSE
filestoai-1.0.0.dist-info/METADATA
filestoai-1.0.0.dist-info/WHEEL
filestoai-1.0.0.dist-info/entry_points.txt
filestoai-1.0.0.dist-info/top_level.txt
filestoai-1.0.0.dist-info/RECORD
