Metadata-Version: 2.4
Name: filestoai
Version: 1.0.0
Summary: Export your codebase for AI consumption - CLI and Web Interface
Home-page: https://github.com/mystxcal/FilesToAI
Author: mystxcal
License: MIT
Project-URL: Homepage, https://github.com/mystxcal/FilesToAI
Project-URL: Repository, https://github.com/mystxcal/FilesToAI
Project-URL: Bug Tracker, https://github.com/mystxcal/FilesToAI/issues
Keywords: ai,codebase,export,cli,llm,chatgpt,claude
Classifier: Development Status :: 4 - Beta
Classifier: Intended Audience :: Developers
Classifier: License :: OSI Approved :: MIT License
Classifier: Programming Language :: Python :: 3
Classifier: Programming Language :: Python :: 3.8
Classifier: Programming Language :: Python :: 3.9
Classifier: Programming Language :: Python :: 3.10
Classifier: Programming Language :: Python :: 3.11
Requires-Python: >=3.8
License-File: LICENSE
Requires-Dist: Flask>=2.3.0
Requires-Dist: keyboard>=0.13.5
Requires-Dist: pyperclip>=1.8.2
Requires-Dist: requests>=2.31.0
Dynamic: home-page
Dynamic: license-file
Dynamic: requires-python
